<?xml version="1.0" encoding="utf-8" ?>
<dwsync>
<file name="script.js" server="ftp.breezecatcher-clothesline.com/mvc-lab_9/" local="130771434648425482" remote="130771182600000000" Dst="2" />
<file name="agency.js" server="ftp.breezecatcher-clothesline.com/mvc_lab_10/" local="130771125568847141" remote="130771670400000000" Dst="2" />
<file name="cbpAnimatedHeader.js" server="ftp.breezecatcher-clothesline.com/mvc_lab_10/" local="130771125557706504" remote="130771670400000000" Dst="2" />
<file name="bootstrap.js" server="ftp.breezecatcher-clothesline.com/mvc_lab_10/" local="130771125571107270" remote="130771670400000000" Dst="2" />
<file name="cbpAnimatedHeader.min.js" server="ftp.breezecatcher-clothesline.com/mvc_lab_10/" local="130771125555396372" remote="130771670400000000" Dst="2" />
<file name="bootstrap.min.js" server="ftp.breezecatcher-clothesline.com/mvc_lab_10/" local="130771125564776908" remote="130771670400000000" Dst="2" />
<file name="classie.js" server="ftp.breezecatcher-clothesline.com/mvc_lab_10/" local="130771125553546266" remote="130771670400000000" Dst="2" />
<file name="contact_me.js" server="ftp.breezecatcher-clothesline.com/mvc_lab_10/" local="130773229848265039" remote="130772977800000000" Dst="2" />
<file name="script.js" server="ftp.breezecatcher-clothesline.com/mvc_lab_10/" local="130771434648425482" remote="130771670400000000" Dst="2" />
<file name="jqBootstrapValidation.js" server="ftp.breezecatcher-clothesline.com/mvc_lab_10/" local="130771125546995891" remote="130771670400000000" Dst="2" />
<file name="jquery.js" server="ftp.breezecatcher-clothesline.com/mvc_lab_10/" local="130771125549326024" remote="130771670400000000" Dst="2" />
<file name="agency.js" server="ftp.breezecatcher-clothesline.com/codeigniter_h/" local="130782879600000000" remote="130782879600000000" Dst="2" />
<file name="bootstrap.js" server="ftp.breezecatcher-clothesline.com/codeigniter_h/" local="130782879600000000" remote="130782879600000000" Dst="2" />
<file name="bootstrap.min.js" server="ftp.breezecatcher-clothesline.com/codeigniter_h/" local="130782879600000000" remote="130782879600000000" Dst="2" />
<file name="cbpAnimatedHeader.js" server="ftp.breezecatcher-clothesline.com/codeigniter_h/" local="130782879600000000" remote="130782879600000000" Dst="2" />
<file name="cbpAnimatedHeader.min.js" server="ftp.breezecatcher-clothesline.com/codeigniter_h/" local="130782879600000000" remote="130782879600000000" Dst="2" />
<file name="classie.js" server="ftp.breezecatcher-clothesline.com/codeigniter_h/" local="130782879600000000" remote="130782879600000000" Dst="2" />
<file name="contact_me.js" server="ftp.breezecatcher-clothesline.com/codeigniter_h/" local="130782879600000000" remote="130782879600000000" Dst="2" />
<file name="jqBootstrapValidation.js" server="ftp.breezecatcher-clothesline.com/codeigniter_h/" local="130782879600000000" remote="130782879600000000" Dst="2" />
<file name="jquery.js" server="ftp.breezecatcher-clothesline.com/codeigniter_h/" local="130782879600000000" remote="130782879600000000" Dst="2" />
<file name="module-bundle-all.js" server="ftp.breezecatcher-clothesline.com/codeigniter_h/" local="130782879600000000" remote="130782879600000000" Dst="2" />
<file name="module-bundle-all.min.js" server="ftp.breezecatcher-clothesline.com/codeigniter_h/" local="130782879600000000" remote="130782879600000000" Dst="2" />
<file name="module-bundle-main.js" server="ftp.breezecatcher-clothesline.com/codeigniter_h/" local="130782879600000000" remote="130782879600000000" Dst="2" />
<file name="module-bundle-main.min.js" server="ftp.breezecatcher-clothesline.com/codeigniter_h/" local="130782879600000000" remote="130782879600000000" Dst="2" />
<file name="module-carousel-slick.js" server="ftp.breezecatcher-clothesline.com/codeigniter_h/" local="130782879600000000" remote="130782879600000000" Dst="2" />
<file name="module-carousel-slick.min.js" server="ftp.breezecatcher-clothesline.com/codeigniter_h/" local="130782879600000000" remote="130782879600000000" Dst="2" />
<file name="module-charts-all.js" server="ftp.breezecatcher-clothesline.com/codeigniter_h/" local="130782880200000000" remote="130782880200000000" Dst="2" />
<file name="module-charts-all.min.js" server="ftp.breezecatcher-clothesline.com/codeigniter_h/" local="130782880200000000" remote="130782880200000000" Dst="2" />
<file name="module-charts-easy-pie.js" server="ftp.breezecatcher-clothesline.com/codeigniter_h/" local="130782880200000000" remote="130782880200000000" Dst="2" />
<file name="module-charts-easy-pie.min.js" server="ftp.breezecatcher-clothesline.com/codeigniter_h/" local="130782880200000000" remote="130782880200000000" Dst="2" />
<file name="module-charts-flot.js" server="ftp.breezecatcher-clothesline.com/codeigniter_h/" local="130782880200000000" remote="130782880200000000" Dst="2" />
<file name="module-charts-flot.min.js" server="ftp.breezecatcher-clothesline.com/codeigniter_h/" local="130782880200000000" remote="130782880200000000" Dst="2" />
<file name="module-charts-morris.js" server="ftp.breezecatcher-clothesline.com/codeigniter_h/" local="130782880200000000" remote="130782880200000000" Dst="2" />
<file name="module-charts-morris.min.js" server="ftp.breezecatcher-clothesline.com/codeigniter_h/" local="130782880200000000" remote="130782880200000000" Dst="2" />
<file name="module-charts-sparkline.js" server="ftp.breezecatcher-clothesline.com/codeigniter_h/" local="130782880200000000" remote="130782880200000000" Dst="2" />
<file name="module-charts-sparkline.min.js" server="ftp.breezecatcher-clothesline.com/codeigniter_h/" local="130782880200000000" remote="130782880200000000" Dst="2" />
<file name="module-chat.js" server="ftp.breezecatcher-clothesline.com/codeigniter_h/" local="130782880200000000" remote="130782880200000000" Dst="2" />
<file name="module-chat.min.js" server="ftp.breezecatcher-clothesline.com/codeigniter_h/" local="130782880200000000" remote="130782880200000000" Dst="2" />
<file name="module-essentials.js" server="ftp.breezecatcher-clothesline.com/codeigniter_h/" local="130782880200000000" remote="130782880200000000" Dst="2" />
<file name="module-essentials.min.js" server="ftp.breezecatcher-clothesline.com/codeigniter_h/" local="130782880200000000" remote="130782880200000000" Dst="2" />
<file name="module-layout.js" server="ftp.breezecatcher-clothesline.com/codeigniter_h/" local="130782880200000000" remote="130782880200000000" Dst="2" />
<file name="module-layout.min.js" server="ftp.breezecatcher-clothesline.com/codeigniter_h/" local="130782880200000000" remote="130782880200000000" Dst="2" />
<file name="module-maps-google.js" server="ftp.breezecatcher-clothesline.com/codeigniter_h/" local="130782880200000000" remote="130782880200000000" Dst="2" />
<file name="module-maps-google.min.js" server="ftp.breezecatcher-clothesline.com/codeigniter_h/" local="130782880200000000" remote="130782880200000000" Dst="2" />
<file name="module-maps.js" server="ftp.breezecatcher-clothesline.com/codeigniter_h/" local="130782880200000000" remote="130782880200000000" Dst="2" />
<file name="module-maps.min.js" server="ftp.breezecatcher-clothesline.com/codeigniter_h/" local="130782880200000000" remote="130782880200000000" Dst="2" />
<file name="module-material.js" server="ftp.breezecatcher-clothesline.com/codeigniter_h/" local="130782880200000000" remote="130782880200000000" Dst="2" />
<file name="module-material.min.js" server="ftp.breezecatcher-clothesline.com/codeigniter_h/" local="130782880200000000" remote="130782880200000000" Dst="2" />
<file name="module-media.js" server="ftp.breezecatcher-clothesline.com/codeigniter_h/" local="130782880200000000" remote="130782880200000000" Dst="2" />
<file name="module-media.min.js" server="ftp.breezecatcher-clothesline.com/codeigniter_h/" local="130782880200000000" remote="130782880200000000" Dst="2" />
<file name="module-messages.js" server="ftp.breezecatcher-clothesline.com/codeigniter_h/" local="130782880200000000" remote="130782880200000000" Dst="2" />
<file name="module-messages.min.js" server="ftp.breezecatcher-clothesline.com/codeigniter_h/" local="130782880200000000" remote="130782880200000000" Dst="2" />
<file name="module-player.js" server="ftp.breezecatcher-clothesline.com/codeigniter_h/" local="130782880200000000" remote="130782880200000000" Dst="2" />
<file name="module-player.min.js" server="ftp.breezecatcher-clothesline.com/codeigniter_h/" local="130782880200000000" remote="130782880200000000" Dst="2" />
<file name="module-sidebar.js" server="ftp.breezecatcher-clothesline.com/codeigniter_h/" local="130782880200000000" remote="130782880200000000" Dst="2" />
<file name="module-sidebar.min.js" server="ftp.breezecatcher-clothesline.com/codeigniter_h/" local="130782880200000000" remote="130782880200000000" Dst="2" />
<file name="script.js" server="ftp.breezecatcher-clothesline.com/codeigniter_h/" local="130782880200000000" remote="130782880200000000" Dst="2" />
<file name="theme-core.js" server="ftp.breezecatcher-clothesline.com/codeigniter_h/" local="130782880200000000" remote="130782880200000000" Dst="2" />
<file name="theme-core.min.js" server="ftp.breezecatcher-clothesline.com/codeigniter_h/" local="130782880200000000" remote="130782880200000000" Dst="2" />
<file name="vendor-bundle-all.js" server="ftp.breezecatcher-clothesline.com/codeigniter_h/" local="130782880200000000" remote="130782880200000000" Dst="2" />
<file name="vendor-bundle-all.min.js" server="ftp.breezecatcher-clothesline.com/codeigniter_h/" local="130782880200000000" remote="130782880200000000" Dst="2" />
<file name="vendor-carousel-slick.js" server="ftp.breezecatcher-clothesline.com/codeigniter_h/" local="130782880200000000" remote="130782880200000000" Dst="2" />
<file name="vendor-carousel-slick.min.js" server="ftp.breezecatcher-clothesline.com/codeigniter_h/" local="130782880200000000" remote="130782880200000000" Dst="2" />
<file name="vendor-charts-all.js" server="ftp.breezecatcher-clothesline.com/codeigniter_h/" local="130782880200000000" remote="130782880200000000" Dst="2" />
<file name="vendor-charts-all.min.js" server="ftp.breezecatcher-clothesline.com/codeigniter_h/" local="130782880200000000" remote="130782880200000000" Dst="2" />
<file name="vendor-charts-flot.js" server="ftp.breezecatcher-clothesline.com/codeigniter_h/" local="130782880200000000" remote="130782880200000000" Dst="2" />
<file name="vendor-charts-flot.min.js" server="ftp.breezecatcher-clothesline.com/codeigniter_h/" local="130782880200000000" remote="130782880200000000" Dst="2" />
<file name="vendor-core.js" server="ftp.breezecatcher-clothesline.com/codeigniter_h/" local="130782880200000000" remote="130782880200000000" Dst="2" />
<file name="vendor-core.min.js" server="ftp.breezecatcher-clothesline.com/codeigniter_h/" local="130782880200000000" remote="130782880200000000" Dst="2" />
<file name="vendor-countdown.js" server="ftp.breezecatcher-clothesline.com/codeigniter_h/" local="130782880200000000" remote="130782880200000000" Dst="2" />
<file name="vendor-countdown.min.js" server="ftp.breezecatcher-clothesline.com/codeigniter_h/" local="130782880200000000" remote="130782880200000000" Dst="2" />
<file name="vendor-forms.min.js" server="ftp.breezecatcher-clothesline.com/codeigniter_h/" local="130782880200000000" remote="130782880200000000" Dst="2" />
<file name="vendor-media.js" server="ftp.breezecatcher-clothesline.com/codeigniter_h/" local="130782880200000000" remote="130782880200000000" Dst="2" />
<file name="vendor-media.min.js" server="ftp.breezecatcher-clothesline.com/codeigniter_h/" local="130782880200000000" remote="130782880200000000" Dst="2" />
<file name="vendor-nestable.js" server="ftp.breezecatcher-clothesline.com/codeigniter_h/" local="130782880200000000" remote="130782880200000000" Dst="2" />
<file name="vendor-nestable.min.js" server="ftp.breezecatcher-clothesline.com/codeigniter_h/" local="130782880200000000" remote="130782880200000000" Dst="2" />
<file name="vendor-player.js" server="ftp.breezecatcher-clothesline.com/codeigniter_h/" local="130782880200000000" remote="130782880200000000" Dst="2" />
<file name="vendor-player.min.js" server="ftp.breezecatcher-clothesline.com/codeigniter_h/" local="130782880200000000" remote="130782880200000000" Dst="2" />
<file name="vendor-tables.js" server="ftp.breezecatcher-clothesline.com/codeigniter_h/" local="130782880200000000" remote="130782880200000000" Dst="2" />
<file name="vendor-tables.min.js" server="ftp.breezecatcher-clothesline.com/codeigniter_h/" local="130782880200000000" remote="130782880200000000" Dst="2" />
<file name="vendor-forms.js" server="ftp.breezecatcher-clothesline.com/codeigniter_h/" local="130783290129989550" remote="130783039800000000" Dst="2" />
<file name="vendor-forms_sav.js" server="ftp.breezecatcher-clothesline.com/codeigniter_h/" local="130783038600000000" remote="130783038600000000" Dst="2" />
</dwsync>